{
  "kind": "collectionType",
  "collectionName": "knowledge_nooks",
  "info": {
    "singularName": "knowledge-nook",
    "pluralName": "knowledge-nooks",
    "displayName": "Knowledge Nook"
  },
  "options": {
    "draftAndPublish": true
  },
  "pluginOptions": {},
  "attributes": {
    "title": {
      "type": "string",
      "required": true
    },
    "description": {
      "type": "text",
      "required": true
    },
    "date": {
      "type": "date",
      "required": true
    },
    "cover": {
      "type": "media",
      "multiple": false,
      "required": true,
      "allowedTypes": [
        "images",
        "files",
        "videos",
        "audios"
      ]
    },
    "download": {
      "type": "media",
      "multiple": false,
      "required": true,
      "allowedTypes": [
        "images",
        "files",
        "videos",
        "audios"
      ]
    }
  }
}
